{"trial_id": "05", "hyperparameters": {"space": [{"class_name": "Int", "config": {"name": "units", "default": null, "conditions": [], "min_value": 32, "max_value": 512, "step": 32, "sampling": "linear"}}, {"class_name": "Float", "config": {"name": "learning_rate", "default": 0.0001, "conditions": [], "min_value": 0.0001, "max_value": 0.01, "step": null, "sampling": "log"}}], "values": {"units": 192, "learning_rate": 0.0002915350155652438}}, "metrics": {"metrics": {"accuracy": {"direction": "max", "observations": [{"value": [0.9773833453655243], "step": 4}]}, "loss": {"direction": "min", "observations": [{"value": [0.07956337928771973], "step": 4}]}, "val_accuracy": {"direction": "max", "observations": [{"value": [0.9728499948978424], "step": 4}]}, "val_loss": {"direction": "min", "observations": [{"value": [0.09110753238201141], "step": 4}]}}}, "score": 0.9728499948978424, "best_step": 4, "status": "COMPLETED", "message": null}